{
  "quotes": [
    {
      "topic": "motivation",
      "quotes": [
        "The only way to do great work is to love what you do. - Steve Jobs",
        "Believe you can and you're halfway there. - Theodore Roosevelt",
        "Success is not final, failure is not fatal: It is the courage to continue that counts. - Winston Churchill"
      ]
    },
    {
      "topic": "love",
      "quotes": [
        "Love is composed of a single soul inhabiting two bodies. - Aristotle",
        "The best thing to hold onto in life is each other. - Audrey Hepburn",
        "We loved with a love that was more than love. - Edgar Allan Poe"
      ]
    }
  ]
}